CHANGELOG
LICENSE
MANIFEST.in
README
defsetup.py
distribute_setup.py
hooks.py
patch_wcslib.sh
setup.cfg
setup.py
stsci_distutils_hack.py
doc/Makefile
doc/docstrings.py
doc/make.bat
doc/source/api.rst
doc/source/api_distortion.rst
doc/source/api_sip.rst
doc/source/api_units.rst
doc/source/api_wcs.rst
doc/source/api_wcsprm.rst
doc/source/conf.py
doc/source/examples.rst
doc/source/index.rst
doc/source/references.rst
doc/source/relax.rst
examples/from_file.py
examples/programmatic.py
lib/pywcs_setup.py
lib/pywcs/__init__.py
lib/pywcs/_docutil.py
lib/pywcs/core.py
lib/pywcs/hooks.py
lib/pywcs/version.py
lib/pywcs.egg-info/PKG-INFO
lib/pywcs.egg-info/SOURCES.txt
lib/pywcs.egg-info/dependency_links.txt
lib/pywcs.egg-info/not-zip-safe
lib/pywcs.egg-info/requires.txt
lib/pywcs.egg-info/top_level.txt
lib/pywcs/tests/__init__.py
lib/pywcs/tests/test.py
lib/pywcs/tests/test_pickle.py
lib/pywcs/tests/test_profiling.py
lib/pywcs/tests/test_wcsprm.py
lib/pywcs/tests/data/3d_cd.hdr
lib/pywcs/tests/data/dist.fits
lib/pywcs/tests/data/outside_sky.hdr
lib/pywcs/tests/data/sip.fits
lib/pywcs/tests/data/sip2.fits
lib/pywcs/tests/maps/1904-66_AIR.hdr
lib/pywcs/tests/maps/1904-66_AIT.hdr
lib/pywcs/tests/maps/1904-66_ARC.hdr
lib/pywcs/tests/maps/1904-66_AZP.hdr
lib/pywcs/tests/maps/1904-66_BON.hdr
lib/pywcs/tests/maps/1904-66_CAR.hdr
lib/pywcs/tests/maps/1904-66_CEA.hdr
lib/pywcs/tests/maps/1904-66_COD.hdr
lib/pywcs/tests/maps/1904-66_COE.hdr
lib/pywcs/tests/maps/1904-66_COO.hdr
lib/pywcs/tests/maps/1904-66_COP.hdr
lib/pywcs/tests/maps/1904-66_CSC.hdr
lib/pywcs/tests/maps/1904-66_CYP.hdr
lib/pywcs/tests/maps/1904-66_HPX.hdr
lib/pywcs/tests/maps/1904-66_MER.hdr
lib/pywcs/tests/maps/1904-66_MOL.hdr
lib/pywcs/tests/maps/1904-66_NCP.hdr
lib/pywcs/tests/maps/1904-66_PAR.hdr
lib/pywcs/tests/maps/1904-66_PCO.hdr
lib/pywcs/tests/maps/1904-66_QSC.hdr
lib/pywcs/tests/maps/1904-66_SFL.hdr
lib/pywcs/tests/maps/1904-66_SIN.hdr
lib/pywcs/tests/maps/1904-66_STG.hdr
lib/pywcs/tests/maps/1904-66_SZP.hdr
lib/pywcs/tests/maps/1904-66_TAN.hdr
lib/pywcs/tests/maps/1904-66_TSC.hdr
lib/pywcs/tests/maps/1904-66_ZEA.hdr
lib/pywcs/tests/maps/1904-66_ZPN.hdr
lib/pywcs/tests/nrao/gls.hdr
