Metadata-Version: 1.1
Name: pywcs
Version: 1.12
Summary: Python wrappers to WCSLIB
Home-page: http://www.scipy.org/AstroLib
Author: Michael Droettboom
Author-email: mdroe@stsci.edu
License: UNKNOWN
Platform: UNKNOWN
Classifier: Intended Audience :: Science/Research
Classifier: License :: OSI Approved :: BSD License
Classifier: Operating System :: OS Independent
Classifier: Programming Language :: Python
Classifier: Topic :: Scientific/Engineering :: Astronomy
Classifier: Topic :: Software Development :: Libraries :: Python Modules
